flask_scheema/__init__.py
flask_scheema/exceptions.py
flask_scheema/flask_extension.py
flask_scheema/logging.py
flask_scheema/utilities.py
flask_scheema/api/__init__.py
flask_scheema/api/api.py
flask_scheema/api/auth.py
flask_scheema/api/auth_routes.py
flask_scheema/api/decorators.py
flask_scheema/api/exception_handling.py
flask_scheema/api/responses.py
flask_scheema/api/utils.py
flask_scheema/html/apispec.html
flask_scheema/html/base_readme.MD
flask_scheema/html/redoc_templates/__init__.py
flask_scheema/html/redoc_templates/aggregate.html
flask_scheema/html/redoc_templates/fields.html
flask_scheema/html/redoc_templates/filters.html
flask_scheema/html/redoc_templates/group.html
flask_scheema/html/redoc_templates/joins.html
flask_scheema/html/redoc_templates/order.html
flask_scheema/scheema/__init__.py
flask_scheema/scheema/bases.py
flask_scheema/scheema/schemas.py
flask_scheema/scheema/utils.py
flask_scheema/services/__init__.py
flask_scheema/services/database.py
flask_scheema/services/operators.py
flask_scheema/specification/__init__.py
flask_scheema/specification/doc_generation.py
flask_scheema/specification/specification.py
flask_scheema/specification/utilities.py
flask_scheema-0.0.7.26.dist-info/LICENCE.rst
flask_scheema-0.0.7.26.dist-info/METADATA
flask_scheema-0.0.7.26.dist-info/WHEEL
flask_scheema-0.0.7.26.dist-info/top_level.txt
flask_scheema-0.0.7.26.dist-info/RECORD
