Metadata-Version: 2.1
Name: flask-scheema
Version: 0.0.7.26
Summary: Automatic RESTful API generator with redoc
Author: arched.dev (Lewis Morris)
Author-email: hello@arched.dev
License: MIT
License-File: LICENCE.rst
Requires-Dist: colorama ==0.4.6
Requires-Dist: numpy ==1.26.4
Requires-Dist: pytest ==8.0.1
Requires-Dist: SQLAlchemy ==2.0.27
Requires-Dist: requests ~=2.31.0
Requires-Dist: bs4 ~=0.0.2
Requires-Dist: beautifulsoup4 ~=4.12.3
Requires-Dist: apispec ==6.4.0
Requires-Dist: Flask ==3.0.2
Requires-Dist: Jinja2 ==3.1.3
Requires-Dist: marshmallow ==3.20.2
Requires-Dist: pytz ==2024.1
Requires-Dist: setuptools ~=68.2.0
Requires-Dist: Werkzeug ~=3.0.1
Requires-Dist: PyJWT ~=2.8.0
Requires-Dist: inflect ~=7.0.0
Requires-Dist: validators ~=0.22.0
Requires-Dist: flask-limiter ~=1.4.0
Requires-Dist: marshmallow-sqlalchemy ~=1.0.0
Requires-Dist: flask-sqlalchemy
Requires-Dist: redis >5.0.0
Requires-Dist: flask-login
Requires-Dist: flask-jwt-extended
